blackbox_logger/__init__.py
blackbox_logger/django_middleware.py
blackbox_logger/django_simple.py
blackbox_logger/logger.py
blackbox_logger/masking.py
blackbox_logger/loggers/__init__.py
blackbox_logger/loggers/file_logger.py
blackbox_logger/loggers/sqlite_logger.py
blackbox_logger-0.2.8.dist-info/METADATA
blackbox_logger-0.2.8.dist-info/WHEEL
blackbox_logger-0.2.8.dist-info/top_level.txt
blackbox_logger-0.2.8.dist-info/RECORD
