Metadata-Version: 2.4
Name: blackbox_logger
Version: 0.2.8
Summary: Framework-agnostic HTTP logger with payload masking
Home-page: https://github.com/avi9r/blackbox_logger
Author: Avinash Ranjan
Author-email: avinashranjan633@gmail.com
License: MIT
Classifier: Programming Language :: Python :: 3
Classifier: License :: OSI Approved :: MIT License
Requires-Python: >=3.6
Dynamic: author
Dynamic: author-email
Dynamic: classifier
Dynamic: description
Dynamic: description-content-type
Dynamic: home-page
Dynamic: license
Dynamic: requires-python
Dynamic: summary
